{"filters":{"$and":[{"$and":[{"municipality.id":{"$eq":"15741"}},{"regio.id":{"$eq":"12"}},{"land.id":{"$eq":"524"}}]}]},"hidden-filters":{"$and":[{"dwellingType.categorie":{"$eq":"woning"}},{"rentBuy":{"$eq":"Huur"}},{"isExtraAanbod":{"$eq":""}},{"isWoningruil":{"$eq":""}},{"$and":[{"$or":[{"street":{"$like":""}},{"houseNumber":{"$like":""}},{"houseNumberAddition":{"$like":""}}]},{"$or":[{"street":{"$like":""}},{"houseNumber":{"$like":""}},{"houseNumberAddition":{"$like":""}}]}]}]},"woningzoekende":{"heeftToegangTotExtraAanbod":false,"huurperiodeVanStartdatum":null,"huurperiodeVanEinddatum":null,"isRechtspersoon":false,"isStudent":false,"isAlleenAccomodate":false,"heeftBlokkade":false,"blokkadeVoorCorporatieIds":null,"huishoudgrootte":1,"aantalMeeverhuizendeKinderen":0,"aantalMeeverhuizendeKinderenOnder18":0,"verzamelinkomen":110985,"heeftEenTMin2Inkomen":false,"heeftElkHuishoudLidOnderbouwdInkomen":true,"leeftijdA1":19,"heeftA2":false,"leeftijdA2":null,"aowLeeftijdBereiktA1":false,"aowLeeftijdBereiktA2":null,"genderIdA1":"1","genderIdA2":null,"startDatumStudieLigtInVoorrangsPeriode":false,"studeertBijOnderwijsinstellingInRegioHaaglanden":false,"woontVerderVanStudieVoorRegioHaaglanden":false,"woontInNederland":true,"studeertBijOnderwijsinstellingVU":false,"studeertBijOnderwijsinstellingACTA":false,"onderwijsinstellingBrincode":null,"studieRegioId":0,"stageRegioId":0,"startdatumStudie":null,"startdatumStage":null,"inschrijvingTypes":[{"inCode":"regulier","id":"1"}],"subtypeInschrijvingId":null,"opleidingstypeId":null,"woontVerderVanOnderwijsinstelling":false,"gemeenteGeoLocatieNaamA1":"Delft","gemeenteIdA1":16044,"soortWoningzoekendeStarterDoorstromer":null,"regioIdA1":7,"regioIdA2":null,"huisnummerA1":"71","huisnummertoevoegingA1":"71-1","postcodeA1":"2628 PZ","huisnummerA2":null,"huisnummertoevoegingA2":null,"postcodeA2":null,"latitudeA1":52.0076,"latitudeA2":null,"longitudeA1":4.36846,"longitudeA2":null,"landIdA1":524,"landIdA2":null,"voorrangen":[],"heeftVermogen":false,"huidigeWoonsituatieId":null,"heeftUitstaandeBetaling":false,"achterlatendeWoningen":null,"vestigingsDatum":null,"eigenaarId":null,"maximaleInschrijftijdEinddatum":null,"eigenWoningId":null},"zoekprofiel":{"locatie":{"regio":[],"municipality":[],"city":[],"neighborhood":[]}}}